deep_sea_treasure/__init__.py
deep_sea_treasure/__version__.py
deep_sea_treasure/contract.py
deep_sea_treasure/deep_sea_treasure_v0.py
deep_sea_treasure/deep_sea_treasure_v0_renderer.py
deep_sea_treasure/fuel_wrapper.py
deep_sea_treasure/outlined_font.py
deep_sea_treasure/py.typed
deep_sea_treasure/theme.py
deep_sea_treasure/vamplew_wrapper.py
deep_sea_treasure/res/__init__.py
deep_sea_treasure/res/submarine.png
deep_sea_treasure/res/treasure.png
deep_sea_treasure/schema/__init__.py
deep_sea_treasure/schema/deep_sea_treasure.schema.json
deep_sea_treasure/schema/fuel_wrapper.schema.json
deep_sea_treasure/schema/vamplew_wrapper.schema.json
deep_sea_treasure-2.0.2.dist-info/LICENSE.md
deep_sea_treasure-2.0.2.dist-info/METADATA
deep_sea_treasure-2.0.2.dist-info/WHEEL
deep_sea_treasure-2.0.2.dist-info/top_level.txt
deep_sea_treasure-2.0.2.dist-info/RECORD
