Metadata-Version: 2.1
Name: deep-sea-treasure
Version: 2.0.2
Summary: An environment for testing multi-objective reinforcement learning algorithms.
Home-page: https://github.com/imec-idlab/deep-sea-treasure
Author: Thomas Cassimon, Reinout Eyckerman
Author-email: thomas.cassimon@uantwerpen.be, reinout.eyckerman@uantwerpen.be
License: UNKNOWN
Project-URL: github, https://github.com/imec-idlab/deep-sea-treasure
Project-URL: zenodo, https://doi.org/10.5281/zenodo.5227091
Keywords: deep,sea,treasure,rl,morl,multi,objective
Platform: UNKNOWN
Classifier: Development Status :: 3 - Alpha
Classifier: Environment :: Console
Classifier: Intended Audience :: Science/Research
Classifier: License :: OSI Approved :: Mozilla Public License 2.0 (MPL 2.0)
Classifier: Natural Language :: English
Classifier: Operating System :: OS Independent
Classifier: Programming Language :: Python :: 3
Classifier: Topic :: Scientific/Engineering :: Artificial Intelligence
Requires-Python: >=3.7
Requires-Dist: gym
Requires-Dist: jsonschema
Requires-Dist: numpy (>=1.21)
Requires-Dist: pygame
